nchu/__init__.py
nchu_sdk-0.2.0.dist-info/LICENSE
nchu_sdk-0.2.0.dist-info/WHEEL
nchu_sdk-0.2.0.dist-info/METADATA
nchu_sdk-0.2.0.dist-info/RECORD
